[{"personName":"Giannis","personSurName":"Polidoras","personAge":42,"personEmail":"giannis.polidoras@example.com"},{"personName":"Maria","personSurName":"Papadopoulou","personAge":35,"personEmail":"maria.papadopoulou@example.com"},{"personName":"Nikos","personSurName":"Kostopoulos","personAge":28,"personEmail":"nikos.kostopoulos@example.com"},{"personName":"Eleni","personSurName":"Georgiou","personAge":31,"personEmail":"eleni.georgiou@example.com"},{"personName":"Dimitris","personSurName":"Alexandris","personAge":45,"personEmail":"dimitris.alexandris@example.com"}]